idaes/__init__.py
idaes/beta.py
idaes/config.py
idaes/conftest.py
idaes/logger.py
idaes/ver.py
idaes/apps/__init__.py
idaes/apps/caprese/categorize.py
idaes/apps/caprese/controller.py
idaes/apps/caprese/dynamic_block.py
idaes/apps/caprese/nmpc.py
idaes/apps/caprese/nmpc_var.py
idaes/apps/caprese/rolling.py
idaes/apps/caprese/util.py
idaes/apps/caprese/common/config.py
idaes/apps/caprese/examples/cstr_model.py
idaes/apps/caprese/examples/cstr_nmpc.py
idaes/apps/caprese/examples/cstr_reduced.py
idaes/apps/caprese/tests/test_categorize.py
idaes/apps/caprese/tests/test_categorize_cstr.py
idaes/apps/caprese/tests/test_controller.py
idaes/apps/caprese/tests/test_dynamic_block.py
idaes/apps/caprese/tests/test_nmpc_var.py
idaes/apps/caprese/tests/test_rolling.py
idaes/apps/caprese/tests/test_simple_model.py
idaes/apps/caprese/tests/test_util.py
idaes/apps/grid_integration/__init__.py
idaes/apps/grid_integration/bidder.py
idaes/apps/grid_integration/coordinator.py
idaes/apps/grid_integration/forecaster.py
idaes/apps/grid_integration/model_data.py
idaes/apps/grid_integration/tracker.py
idaes/apps/grid_integration/utils.py
idaes/apps/grid_integration/examples/__init__.py
idaes/apps/grid_integration/examples/thermal_generator.py
idaes/apps/grid_integration/examples/thermal_generator_prescient_plugin.py
idaes/apps/grid_integration/examples/utils.py
idaes/apps/grid_integration/multiperiod/__init__.py
idaes/apps/grid_integration/multiperiod/multiperiod.py
idaes/apps/grid_integration/multiperiod/tests/__init__.py
idaes/apps/grid_integration/multiperiod/tests/test_multiperiod.py
idaes/apps/grid_integration/pricetaker/__init__.py
idaes/apps/grid_integration/pricetaker/clustering.py
idaes/apps/grid_integration/pricetaker/design_and_operation_models.py
idaes/apps/grid_integration/pricetaker/price_taker_model.py
idaes/apps/grid_integration/pricetaker/unit_commitment.py
idaes/apps/grid_integration/pricetaker/tests/__init__.py
idaes/apps/grid_integration/pricetaker/tests/lmp_data.csv
idaes_pse-2.9.0.dist-info/licenses/LICENSE.md
idaes_pse-2.9.0.dist-info/METADATA
idaes_pse-2.9.0.dist-info/WHEEL
idaes_pse-2.9.0.dist-info/entry_points.txt
idaes_pse-2.9.0.dist-info/top_level.txt
idaes_pse-2.9.0.dist-info/RECORD
