Metadata-Version: 2.4
Name: idaes-pse
Version: 2.9.0
Summary: IDAES Process Systems Engineering Framework
Home-page: https://idaes.org
Maintainer: Keith Beattie
Maintainer-email: ksbeattie@lbl.gov
License: BSD 
Keywords: idaes-pse,energy systems,chemical engineering,process modeling
Platform: any
Classifier: Development Status :: 5 - Production/Stable
Classifier: Intended Audience :: End Users/Desktop
Classifier: Intended Audience :: Science/Research
Classifier: License :: OSI Approved :: BSD License
Classifier: Natural Language :: English
Classifier: Operating System :: MacOS
Classifier: Operating System :: Microsoft :: Windows
Classifier: Operating System :: Unix
Classifier: Programming Language :: Python
Classifier: Programming Language :: Python :: 3
Classifier: Programming Language :: Python :: 3.9
Classifier: Programming Language :: Python :: 3.10
Classifier: Programming Language :: Python :: 3.11
Classifier: Programming Language :: Python :: 3.12
Classifier: Programming Language :: Python :: 3.13
Classifier: Programming Language :: Python :: Implementation :: CPython
Classifier: Topic :: Scientific/Engineering :: Mathematics
Classifier: Topic :: Scientific/Engineering :: Chemistry
Classifier: Topic :: Software Development :: Libraries :: Python Modules
License-File: LICENSE.md
Requires-Dist: pyomo>=6.9.3
Requires-Dist: pint>=0.24.1
Requires-Dist: networkx
Requires-Dist: numpy<3,>=1
Requires-Dist: pandas!=2.1.0,<3
Requires-Dist: scipy
Requires-Dist: sympy
Requires-Dist: matplotlib
Requires-Dist: click>=8
Provides-Extra: ui
Requires-Dist: idaes-ui; extra == "ui"
Provides-Extra: omlt
Requires-Dist: omlt==1.1; extra == "omlt"
Requires-Dist: tensorflow; extra == "omlt"
Requires-Dist: onnx; extra == "omlt"
Provides-Extra: grid
Requires-Dist: gridx-prescient>=2.2.1; extra == "grid"
Provides-Extra: coolprop
Requires-Dist: coolprop>=7.0; extra == "coolprop"
Provides-Extra: testing
Requires-Dist: pytest; extra == "testing"
Requires-Dist: addheader; extra == "testing"
Requires-Dist: pyyaml; extra == "testing"
Dynamic: classifier
Dynamic: description
Dynamic: description-content-type
Dynamic: home-page
Dynamic: keywords
Dynamic: license
Dynamic: license-file
Dynamic: maintainer
Dynamic: maintainer-email
Dynamic: platform
Dynamic: provides-extra
Dynamic: requires-dist
Dynamic: summary
